<RECORD ID="650">
<TEXT>
<ID>158011729</ID>
<HOSPITAL>CMC</HOSPITAL>
CORONARY ARTERY DISEASE
Signed
DIS
<DATE>07/17/1998</DATE>
Report Status :
Discharge Date :
<DATE>07/27/1998</DATE>
SECONDARY DIAGNOSES :
(2) NON-INSULIN DEPENDENT DIABETES MELLITUS .
(3) HYPERTENSION .
Mr. <PATIENT>Tlandpiernshi</PATIENT> is a 64 year old gentleman , with a history of CHF and new non-Q wave myocardial infarction .
His cardiology workup revealed significant three vessel coronary artery disease and the patient was referred to the <HOSPITAL>Camweissallcoa Medical Center</HOSPITAL> for myocardial revascularization .
MEDICATIONS :
IV heparin , IV TNG ; atenolol 50 mg p.o. b.i.d.; glyburide 10 mg p.o. b.i.d.; Mevacor 20 mg p.o. q.d.;Lasix 40 mg p.o. q.d.; ECASA 325 mg p.o. q.d.; KCl 25 mEq p.o.q.d.; Vasotec 5 mg p.o. b.i.d.; Xalatan .
PHYSICAL EXAMINATION :
GENERAL :
Pleasant , somewhat confused 69 year old gentleman with no new focal neurological deficits .
NECK :
Supple , no bruits of carotidarteries .
LUNGS :
No murmur .
ABDOMEN :
Soft , non-tender , and benign .
No evidence of edema or varicoses .
The surgeon was Dr. <DOCTOR>Leub</DOCTOR> .
His initial postoperative recovery was uneventful .
The patient showed no signs of ischemia .
Further recovery in the Stepdown Unit was not associated with any significant complications .
This resulted inconversion and stable therapy with Lopressor .
In the absence of the signs of the wound infection and the stable postoperative course , the decision was made to transfer Mr. <PATIENT>Tlandpiernshi</PATIENT> to the rehabilitation facility on <DATE>7/25/98</DATE> in a stable postoperative condition , with the following medications :
Colace 100 mg p.o. t.i.d.; glyburide 10 mg p.o. b.i.d.; Mevacor 20 mg p.o. q.d.;Lopressor 50 mg p.o. b.i.d.; Warfarin ; Coumadin p.o. q.d. , goal INRis 2-2.5 ; Xalatan 1 drop OU q.p.m.; Alphegan 1 drop OU q.d.;Tylenol ES 500-1000 mg p.o. q.4-6h. p.r.n. pain ; Lasix 40 mg p.o.q.d.
Stable condition .
The patient was discharged to rehab facility in <HOSPITAL>Macan Hospital</HOSPITAL> , <LOCATION>San Dr. , Lakea Satole , Georgia 97746</LOCATION> .
Phone# <PHONE>(139) 667-6656</PHONE> .
Dictated By :
<DOCTOR>KA NETELINKEFUSCKOTE</DOCTOR> , M.D. <ID>QS07</ID>
Batch :
Index No.
<DATE>07/25/98</DATE>
T :
<DATE>07/25/98</DATE>
</TEXT>
</RECORD>