{"signal": "\n\nHLGMC\n1885323\n085995\nFAILED LEFT TOTAL HIP REPLACEMENT .\nDIS\nReport Status :\nLYSSFUST , NY\nUNIT NUMBER :\n096-50-15\nADMISSION DATE :\nPRINCIPAL DIAGNOSIS :\nFailed left total hip replacement .\nPRINCIPAL PROCEDURE :\nLeft total hip replacement revision .\nATTENDING PHYSICIAN :\nLi Rhalttland , M.D.\nHISTORY OF PRESENT ILLNESS :\nThis is a 66-year-old Caucasian woman with a history of recurrent left hip dislocations .\nShe 's had multiple medical problems including a severe chronic obstructive pulmonary disease and insulin dependent diabetes mellitus .\nShe has a right hip dynamic hip screw in place for the intertrochanteric fracture .\nThe left total hip replacement now needs revision due to the multiple dislocations .\nPAST MEDICAL HISTORY :\nInsulin dependent diabetes mellitus , hypertension , severe chronic obstructive pulmonary disease , remote history of ethanol abuse , history of thrombocytopenia .\nPAST SURGICAL HISTORY :\nLeft hip replacement 30 years ago , revised 10 or 15 years later and multiple dislocations ever since .\nShe is status post appendectomy , status post hysterectomy .\nMEDICATIONS ON ADMISSION :\nNystatin powder to groin and lobular area b.i.d. prn .\nInsulin NPH 32 units q.a.m. , regular 10 units q.a.m.\nZestril 10 mg. PO t.i.d.\nAldactone 25 mg. PO q.day .\nAtrovent metered dose inhaler 2 puffs inhaled q.i.d.\nPercocet 1-2 tablets PO q.6 hours prn .\nWell butrin slow release 150 mg. PO b.i.d. Os - Cal 500mg. PO b.i.d.\nVitamin D 1 tablet PO q.day .\nMultivitamin 1 tablet PO q.day .\nZinc sulfate 220 mg. PO t.i.d.\nVitamin C 500 mg. PO b.i.d.\nPromod2 scoops PO t.i.d. in water or OJ .\nTwo pack a day smoker x40 years .\nA history of ethanol use .\nAmount unspecified .\nLives with her husband in Bayont .\nPHYSICAL EXAMINATION :\nShe is afebrile .\nThe vital signs are stable .\nThe head and neck exam notable for very poor dentition , no dentures .\nShe wears glasses .\nThere is no evidence of lymphadenopathy .\nNeck is supple .\nPulmonary exam notable for decreased breath sounds bilaterally in the lower lobes .\nCardiac :\nAbdomen :\nobese , present bowel sounds , noorganomegaly , no masses .\nUpper extremities :\nnormal , full range of motion , sensation and motor exam .\nThe lower extremities :\nright shows a well healed incision consistent with her dynamic hip screw placement .\nQuads and abductors 4/5 strength , extensor hallucis longus and hamstrings , flexor hallucis longus , tib and gastrocnemius , soleus 5/5 in strength .\nSensation is intact , 1+ dorsalis pedis pulses .\nFull range of motion in the right hip .\nLeft hip :\nwell healed incision , quads , abductors , ileus , psoas 4/5 , hamstring , extensor hallucis longus , left HL , gastroc , soleus 4+/5 .\nFlexion goes to 70 degrees adduction , 10 degrees abduction , 30 degrees internal rotation , 10 degrees external rotation , 15 degrees .\nSensation is intact distally .\nHOSPITAL COURSE AND TREATMENT :\nOn 12/14/98 the patient underwent revision left total hip replacement .\nThe patient tolerated the procedure well and postoperatively was hemodynamically stable with a hematocrit of 31 and stable vital signs .\nThe decision was made to give her two units of packed red blood cells due to a borderline hypotension .\nShe was seen by both Diabetes and Pulmonary Services who recommended appropriate adjustment of her insulin doses as well as her pulmonary issues ; primarily she was treated with nebulizers and inhalers as well as chest physical therapy and had no pulmonary complications .\nShe was slow to mobilize with physical therapy due to weakness and proprioceptive difficulties .\nUrine culture grew Enterococcus .\nDr. Stable elected to start her on Bactrim for a five day course .\nShe had been on Macrodantin suppressive therapy preoperatively .\nPrior to discharge , lower extremity noninvasive studies were done to rule out deep venous thrombosis , the results of which are pending at this time .\nCoumadin 0.5 mg. PO q.p.m. x3 weeks .\nInsulin NPH 45 units subcutaneous q.a.m. , regular insulin 20 units subcutaneous q.a.m. in addition to a sliding scale .\nIn the evening she gets regular insulin 10 units subcutaneous before supper with a sliding scale .\nThe CZI scale is as follows :\nfor blood sugar 201-250 5 units , 251-300 8 units , 301-350 12 units , 351-400 15 units and greater than 400 18 units .\nZestril10 mg. PO b.i.d.\nAldactone 25 mg. PO q.day .\nLasix 20 mg. PO q.day .\nAtrovent metered dose inhaler 2 puffs q.i.d. prn .\nWell butrin slow release 150 mg. PO b.i.d.\nVitamin D 1 tablet PO q.day .\nBactrim 1 tablet double strength b.i.d. x4 days .\nColace 100 mg. PO b.i.d.\nPercocet 1-2 tablets PO q.4 hours prn pain .\nShe gets a 1500 cal ADA diet .\nShe will be transferred to rehabilitation with dislocation precautions , left partial weight bearing will be allowed .\nStaples may be removed at the 12th to 14th day postoperative point .\nPT INR levels should be checked twice a week , the results which should be called to Dr. Stable 's office , 495-3401 .\nGoal INR should be between 1.5 and 2.0 and she will continue on Coumadin for three more weeks .\nFOLLOW UP :\nA follow up with Dr. Stable 's office should be scheduled for six weeks from the time of surgery and she should call both her Pulmonologist and Diabetes Specialist for follow up within the next one to two weeks .\nVITRA E. LINKE , M.D.\nDICTATING FOR :\nLI R. STABLE , M.D.\ndju\nDD :\n12/17/98\nTD :\n12/17/98 4:14\nLI RIJARRED STABLE , M.D. STAT\n\n\n", "asets": [{"hasID": false, "type": "lex", "attrs": [], "annots": [[2, 7], [8, 15], [16, 22], [23, 29], [30, 34], [35, 40], [41, 44], [45, 56], [57, 58], [59, 62], [63, 69], [70, 76], [77, 78], [79, 87], [88, 89], [90, 92], [93, 97], [98, 104], [105, 106], [107, 116], [117, 126], [127, 131], [132, 133], [134, 143], [144, 153], [154, 155], [156, 162], [163, 167], [168, 173], [174, 177], [178, 189], [190, 191], [192, 201], [202, 211], [212, 213], [214, 218], [219, 224], [225, 228], [229, 240], [241, 249], [250, 251], [252, 261], [262, 271], [272, 273], [274, 276], [277, 287], [288, 289], [290, 292], [292, 294], [295, 302], [303, 305], [306, 313], [314, 321], [322, 323], [324, 328], [329, 331], [332, 333], [334, 336], [336, 345], [346, 355], [356, 361], [362, 366], [367, 368], [369, 376], [377, 379], [380, 389], [390, 394], [395, 398], [399, 411], [412, 413], [414, 417], [418, 420], [421, 424], [425, 433], [434, 441], [442, 450], [451, 460], [461, 462], [463, 469], [470, 477], [478, 489], [490, 499], [500, 507], [508, 511], [512, 519], [520, 529], [530, 538], [539, 547], [548, 549], [550, 553], [554, 557], [558, 559], [560, 565], [566, 569], [570, 577], [578, 581], [582, 587], [588, 590], [591, 596], [597, 600], [601, 604], [605, 622], [623, 631], [632, 633], [634, 637], [638, 642], [643, 648], [649, 652], [653, 664], [665, 668], [669, 674], [675, 683], [684, 687], [688, 690], [691, 694], [695, 703], [704, 716], [717, 718], [719, 723], [724, 731], [732, 739], [740, 741], [742, 749], [750, 759], [760, 768], [769, 777], [778, 779], [780, 792], [793, 794], [795, 801], [802, 809], [810, 821], [822, 831], [832, 839], [840, 841], [842, 848], [849, 856], [857, 859], [860, 867], [868, 873], [874, 875], [876, 883], [884, 886], [887, 903], [904, 905], [906, 910], [911, 919], [920, 927], [928, 929], [930, 934], [935, 938], [939, 950], [951, 953], [954, 959], [960, 963], [964, 965], [966, 973], [974, 976], [977, 979], [980, 982], [983, 988], [989, 994], [995, 998], [999, 1007], [1008, 1020], [1021, 1025], [1026, 1031], [1032, 1033], [1034, 1037], [1038, 1040], [1041, 1047], [1048, 1052], [1053, 1065], [1066, 1067], [1068, 1074], [1075, 1079], [1080, 1092], [1093, 1094], [1095, 1106], [1107, 1109], [1110, 1119], [1120, 1121], [1122, 1130], [1131, 1137], [1138, 1140], [1141, 1146], [1147, 1150], [1151, 1158], [1159, 1163], [1164, 1166], [1166, 1168], [1168, 1170], [1171, 1174], [1175, 1176], [1177, 1184], [1185, 1188], [1189, 1191], [1192, 1197], [1198, 1200], [1200, 1202], [1202, 1204], [1205, 1206], [1207, 1214], [1215, 1217], [1218, 1223], [1224, 1226], [1226, 1228], [1228, 1230], [1231, 1238], [1239, 1241], [1242, 1244], [1244, 1245], [1246, 1248], [1249, 1251], [1251, 1253], [1253, 1255], [1256, 1265], [1266, 1268], [1269, 1271], [1271, 1272], [1273, 1275], [1276, 1278], [1278, 1281], [1282, 1283], [1284, 1292], [1293, 1300], [1301, 1305], [1306, 1313], [1314, 1315], [1316, 1321], [1322, 1329], [1330, 1332], [1332, 1334], [1334, 1336], [1337, 1345], [1346, 1349], [1350, 1357], [1358, 1360], [1361, 1363], [1363, 1364], [1365, 1370], [1371, 1374], [1375, 1376], [1377, 1381], [1382, 1388], [1389, 1393], [1394, 1401], [1402, 1405], [1406, 1408], [1408, 1409], [1410, 1412], [1413, 1415], [1415, 1417], [1417, 1419], [1420, 1422], [1423, 1424], [1425, 1428], [1429, 1434], [1434, 1435], [1436, 1438], [1439, 1441], [1441, 1443], [1443, 1445], [1446, 1453], [1454, 1455], [1456, 1457], [1458, 1464], [1465, 1467], [1468, 1470], [1470, 1473], [1474, 1475], [1476, 1488], [1489, 1490], [1491, 1497], [1498, 1500], [1501, 1503], [1503, 1506], [1507, 1508], [1509, 1513], [1514, 1521], [1522, 1525], [1526, 1528], [1528, 1529], [1530, 1532], [1533, 1535], [1535, 1537], [1537, 1539], [1540, 1547], [1548, 1549], [1550, 1553], [1554, 1556], [1556, 1557], [1558, 1560], [1561, 1563], [1563, 1565], [1565, 1567], [1568, 1575], [1576, 1582], [1583, 1585], [1586, 1588], [1588, 1590], [1590, 1592], [1593, 1595], [1596, 1601], [1602, 1604], [1605, 1607], [1608, 1609], [1610, 1613], [1614, 1618], [1619, 1620], [1621, 1624], [1625, 1631], [1632, 1635], [1636, 1641], [1642, 1643], [1644, 1645], [1646, 1653], [1654, 1656], [1657, 1664], [1665, 1668], [1669, 1670], [1671, 1677], [1678, 1689], [1690, 1691], [1692, 1697], [1698, 1702], [1703, 1706], [1707, 1714], [1715, 1717], [1718, 1724], [1725, 1726], [1727, 1735], [1736, 1747], [1748, 1749], [1750, 1753], [1754, 1756], [1757, 1765], [1766, 1767], [1768, 1771], [1772, 1777], [1778, 1783], [1784, 1787], [1788, 1794], [1795, 1796], [1797, 1800], [1801, 1805], [1806, 1809], [1810, 1814], [1815, 1819], [1820, 1827], [1828, 1831], [1832, 1836], [1837, 1841], [1842, 1851], [1852, 1853], [1854, 1856], [1857, 1865], [1866, 1867], [1868, 1871], [1872, 1877], [1878, 1885], [1886, 1887], [1888, 1893], [1894, 1896], [1897, 1899], [1900, 1908], [1909, 1911], [1912, 1927], [1928, 1929], [1930, 1934], [1935, 1937], [1938, 1944], [1945, 1946], [1947, 1956], [1957, 1961], [1962, 1969], [1970, 1973], [1974, 1983], [1984, 1990], [1991, 1997], [1998, 2009], [2010, 2012], [2013, 2016], [2017, 2022], [2023, 2028], [2029, 2030], [2031, 2038], [2039, 2040], [2041, 2048], [2049, 2050], [2051, 2056], [2057, 2058], [2059, 2066], [2067, 2072], [2073, 2079], [2080, 2081], [2082, 2096], [2097, 2098], [2099, 2101], [2102, 2108], [2109, 2110], [2111, 2116], [2117, 2128], [2129, 2130], [2131, 2137], [2138, 2139], [2140, 2144], [2145, 2150], [2151, 2153], [2154, 2160], [2161, 2162], [2163, 2172], [2173, 2176], [2177, 2182], [2183, 2187], [2188, 2189], [2190, 2193], [2194, 2199], [2200, 2211], [2212, 2213], [2214, 2219], [2220, 2225], [2226, 2227], [2228, 2232], [2233, 2239], [2240, 2248], [2249, 2259], [2260, 2264], [2265, 2268], [2269, 2276], [2277, 2280], [2281, 2286], [2287, 2296], [2297, 2298], [2299, 2304], [2305, 2308], [2309, 2318], [2319, 2320], [2320, 2321], [2321, 2322], [2323, 2331], [2332, 2333], [2334, 2342], [2343, 2351], [2352, 2358], [2359, 2362], [2363, 2373], [2374, 2375], [2376, 2382], [2383, 2391], [2392, 2398], [2399, 2400], [2401, 2404], [2405, 2408], [2409, 2422], [2423, 2424], [2425, 2431], [2432, 2433], [2433, 2434], [2434, 2435], [2436, 2438], [2439, 2447], [2448, 2449], [2450, 2459], [2460, 2462], [2463, 2469], [2470, 2471], [2472, 2473], [2473, 2474], [2475, 2483], [2484, 2489], [2490, 2496], [2497, 2498], [2499, 2503], [2504, 2509], [2510, 2512], [2513, 2519], [2520, 2522], [2523, 2526], [2527, 2532], [2533, 2536], [2537, 2538], [2539, 2543], [2544, 2547], [2548, 2549], [2550, 2554], [2555, 2561], [2562, 2570], [2571, 2572], [2573, 2578], [2579, 2580], [2581, 2590], [2591, 2592], [2593, 2598], [2599, 2600], [2601, 2606], [2607, 2608], [2608, 2609], [2609, 2610], [2611, 2612], [2613, 2622], [2623, 2624], [2625, 2633], [2634, 2642], [2643, 2649], [2650, 2651], [2652, 2656], [2657, 2659], [2660, 2661], [2662, 2669], [2670, 2671], [2672, 2678], [2679, 2680], [2680, 2682], [2682, 2683], [2684, 2685], [2686, 2693], [2694, 2698], [2699, 2701], [2702, 2704], [2705, 2712], [2713, 2722], [2723, 2724], [2725, 2727], [2728, 2735], [2736, 2745], [2746, 2747], [2748, 2750], [2751, 2758], [2759, 2767], [2768, 2776], [2777, 2778], [2779, 2781], [2782, 2789], [2790, 2798], [2799, 2807], [2808, 2809], [2810, 2812], [2813, 2820], [2821, 2822], [2823, 2832], [2833, 2835], [2836, 2842], [2843, 2851], [2852, 2853], [2854, 2862], [2863, 2869], [2870, 2873], [2874, 2883], [2884, 2885], [2886, 2888], [2889, 2891], [2891, 2892], [2892, 2894], [2894, 2895], [2895, 2897], [2898, 2901], [2902, 2909], [2910, 2919], [2920, 2928], [2929, 2933], [2934, 2939], [2940, 2943], [2944, 2955], [2956, 2957], [2958, 2961], [2962, 2969], [2970, 2979], [2980, 2983], [2984, 2993], [2994, 2998], [2999, 3002], [3003, 3018], [3019, 3022], [3023, 3038], [3039, 3045], [3046, 3050], [3051, 3052], [3053, 3063], [3064, 3066], [3067, 3069], [3070, 3073], [3074, 3080], [3081, 3086], [3087, 3092], [3093, 3094], [3095, 3098], [3099, 3107], [3108, 3111], [3112, 3116], [3117, 3119], [3120, 3124], [3125, 3128], [3129, 3132], [3133, 3138], [3139, 3141], [3142, 3148], [3149, 3152], [3153, 3158], [3159, 3164], [3165, 3168], [3169, 3171], [3172, 3173], [3174, 3184], [3185, 3196], [3197, 3198], [3199, 3202], [3203, 3206], [3207, 3211], [3212, 3214], [3215, 3219], [3220, 3228], [3229, 3232], [3233, 3242], [3243, 3251], [3252, 3255], [3256, 3267], [3268, 3279], [3280, 3290], [3291, 3293], [3294, 3297], [3298, 3305], [3306, 3311], [3312, 3314], [3315, 3319], [3320, 3322], [3323, 3326], [3327, 3336], [3337, 3343], [3344, 3345], [3346, 3355], [3356, 3359], [3360, 3363], [3364, 3371], [3372, 3376], [3377, 3387], [3388, 3391], [3392, 3400], [3401, 3403], [3404, 3408], [3409, 3411], [3412, 3417], [3418, 3426], [3427, 3434], [3435, 3438], [3439, 3442], [3443, 3445], [3446, 3455], [3456, 3469], [3470, 3471], [3472, 3475], [3476, 3479], [3480, 3484], [3485, 3487], [3488, 3496], [3497, 3501], [3502, 3510], [3511, 3518], [3519, 3522], [3523, 3525], [3526, 3534], [3535, 3538], [3539, 3553], [3554, 3566], [3567, 3568], [3569, 3574], [3575, 3582], [3583, 3587], [3588, 3600], [3601, 3602], [3603, 3606], [3607, 3613], [3614, 3621], [3622, 3624], [3625, 3630], [3631, 3634], [3635, 3637], [3638, 3645], [3646, 3649], [3650, 3651], [3652, 3656], [3657, 3660], [3661, 3667], [3668, 3669], [3670, 3673], [3674, 3677], [3678, 3682], [3683, 3685], [3686, 3697], [3698, 3709], [3710, 3717], [3718, 3732], [3733, 3734], [3735, 3740], [3741, 3743], [3744, 3753], [3754, 3755], [3756, 3761], [3762, 3771], [3772, 3783], [3784, 3791], [3792, 3796], [3797, 3801], [3802, 3804], [3805, 3809], [3810, 3813], [3814, 3818], [3819, 3825], [3826, 3836], [3837, 3838], [3839, 3842], [3843, 3850], [3851, 3853], [3854, 3859], [3860, 3863], [3864, 3871], [3872, 3874], [3875, 3879], [3880, 3884], [3885, 3886], [3887, 3895], [3896, 3899], [3900, 3902], [3902, 3903], [3904, 3906], [3907, 3909], [3909, 3911], [3911, 3913], [3914, 3916], [3917, 3922], [3923, 3924], [3925, 3932], [3933, 3936], [3937, 3939], [3940, 3945], [3946, 3958], [3959, 3961], [3961, 3963], [3963, 3965], [3966, 3967], [3968, 3975], [3976, 3983], [3984, 3986], [3987, 3992], [3993, 4005], [4006, 4008], [4008, 4010], [4010, 4012], [4013, 4015], [4016, 4024], [4025, 4027], [4028, 4029], [4030, 4037], [4038, 4043], [4044, 4045], [4046, 4048], [4049, 4052], [4053, 4060], [4061, 4064], [4065, 4069], [4070, 4077], [4078, 4085], [4086, 4088], [4089, 4094], [4095, 4107], [4108, 4114], [4115, 4121], [4122, 4126], [4127, 4128], [4129, 4136], [4137, 4142], [4143, 4144], [4145, 4148], [4149, 4152], [4153, 4158], [4159, 4161], [4162, 4164], [4165, 4172], [4173, 4174], [4175, 4178], [4179, 4184], [4185, 4190], [4191, 4198], [4199, 4200], [4201, 4206], [4207, 4208], [4209, 4216], [4217, 4218], [4219, 4224], [4225, 4226], [4227, 4234], [4235, 4237], [4238, 4243], [4244, 4245], [4246, 4253], [4254, 4256], [4257, 4262], [4263, 4266], [4267, 4274], [4275, 4279], [4280, 4283], [4284, 4286], [4287, 4292], [4293, 4294], [4295, 4304], [4305, 4307], [4307, 4308], [4309, 4311], [4312, 4314], [4314, 4316], [4316, 4318], [4319, 4328], [4329, 4331], [4332, 4334], [4334, 4335], [4336, 4338], [4339, 4341], [4341, 4344], [4345, 4346], [4347, 4352], [4353, 4355], [4356, 4358], [4358, 4359], [4360, 4362], [4363, 4365], [4365, 4368], [4369, 4370], [4371, 4379], [4380, 4387], [4388, 4392], [4393, 4400], [4401, 4402], [4403, 4408], [4409, 4411], [4411, 4413], [4413, 4415], [4416, 4419], [4420, 4421], [4422, 4426], [4427, 4433], [4434, 4438], [4439, 4446], [4447, 4450], [4451, 4453], [4453, 4454], [4455, 4457], [4458, 4460], [4460, 4462], [4462, 4464], [4465, 4472], [4473, 4474], [4475, 4476], [4477, 4483], [4484, 4486], [4487, 4489], [4489, 4492], [4493, 4494], [4495, 4502], [4503, 4504], [4505, 4511], [4512, 4518], [4519, 4527], [4528, 4530], [4530, 4532], [4532, 4534], [4535, 4537], [4538, 4542], [4543, 4544], [4545, 4551], [4552, 4555], [4556, 4558], [4558, 4559], [4560, 4562], [4563, 4565], [4565, 4567], [4567, 4569], [4570, 4578], [4579, 4582], [4583, 4590], [4591, 4593], [4594, 4596], [4596, 4597], [4598, 4603], [4604, 4607], [4608, 4612], [4613, 4614], [4615, 4618], [4619, 4623], [4624, 4625], [4626, 4630], [4631, 4634], [4635, 4638], [4639, 4643], [4644, 4645], [4646, 4649], [4650, 4654], [4655, 4657], [4658, 4669], [4670, 4672], [4673, 4687], [4688, 4692], [4693, 4704], [4705, 4716], [4717, 4718], [4719, 4723], [4724, 4731], [4732, 4738], [4739, 4746], [4747, 4751], [4752, 4754], [4755, 4762], [4763, 4764], [4765, 4772], [4773, 4776], [4777, 4779], [4780, 4787], [4788, 4790], [4791, 4794], [4795, 4799], [4800, 4802], [4803, 4807], [4808, 4811], [4812, 4825], [4826, 4831], [4832, 4833], [4834, 4836], [4837, 4840], [4841, 4847], [4848, 4854], [4855, 4857], [4858, 4865], [4866, 4871], [4872, 4873], [4874, 4878], [4879, 4880], [4881, 4884], [4885, 4892], [4893, 4898], [4899, 4905], [4906, 4908], [4909, 4915], [4916, 4918], [4919, 4922], [4923, 4929], [4930, 4932], [4933, 4939], [4940, 4941], [4942, 4950], [4951, 4952], [4953, 4957], [4958, 4961], [4962, 4968], [4969, 4971], [4972, 4979], [4980, 4983], [4984, 4987], [4988, 4991], [4992, 4995], [4996, 4999], [5000, 5004], [5005, 5013], [5014, 5016], [5017, 5025], [5026, 5029], [5030, 5035], [5036, 5040], [5041, 5046], [5047, 5048], [5049, 5055], [5056, 5058], [5059, 5060], [5061, 5062], [5063, 5069], [5070, 5072], [5073, 5077], [5078, 5081], [5082, 5088], [5089, 5091], [5092, 5098], [5099, 5105], [5106, 5108], [5109, 5118], [5119, 5122], [5123, 5126], [5127, 5132], [5133, 5137], [5138, 5141], [5142, 5146], [5147, 5149], [5150, 5157], [5158, 5161], [5162, 5165], [5166, 5172], [5173, 5177], [5178, 5182], [5183, 5186], [5187, 5200], [5201, 5204], [5205, 5213], [5214, 5224], [5225, 5228], [5229, 5235], [5236, 5238], [5239, 5245], [5246, 5249], [5250, 5254], [5255, 5258], [5259, 5261], [5262, 5265], [5266, 5271], [5272, 5273], [5274, 5279], [5280, 5282], [5283, 5288], [5289, 5290], [5291, 5293], [5293, 5295], [5296, 5305], [5306, 5309], [5310, 5311], [5312, 5314], [5315, 5317], [5318, 5324], [5325, 5326], [5327, 5329], [5329, 5331], [5332, 5335], [5336, 5338], [5339, 5340], [5341, 5343], [5343, 5344], [5344, 5346], [5346, 5347], [5347, 5349], [5350, 5352], [5353, 5354], [5355, 5357], [5357, 5358], [5358, 5360], [5360, 5361], [5361, 5363], [5364, 5365], [5365, 5366], [5366, 5368], [5369, 5371], [5372, 5380], [5381, 5387], [5388, 5389], [5390, 5392], [5392, 5394], [5395, 5399]], "hasSpan": true}, {"hasID": false, "type": "zone", "attrs": [{"type": "string", "name": "region_type", "aggregation": null}], "annots": [[0, 5402, "body"]], "hasSpan": true}, {"hasID": false, "type": "ID", "attrs": [], "annots": [[8, 15], [16, 22], [107, 116]], "hasSpan": true}, {"hasID": false, "type": "DATE", "attrs": [], "annots": [[2889, 2897], [5341, 5349], [5355, 5363]], "hasSpan": true}, {"hasID": false, "type": "PATIENT", "attrs": [], "annots": [[79, 92]], "hasSpan": true}, {"hasID": false, "type": "LOCATION", "attrs": [], "annots": [[1718, 1724]], "hasSpan": true}, {"hasID": false, "type": "DOCTOR", "attrs": [], "annots": [[274, 287], [3607, 3613], [4923, 4929], [5082, 5088], [5274, 5288], [5312, 5324], [5332, 5335], [5369, 5387]], "hasSpan": true}, {"hasID": false, "type": "HOSPITAL", "attrs": [], "annots": [[2, 7]], "hasSpan": true}, {"hasID": false, "type": "PHONE", "attrs": [], "annots": [[4942, 4950]], "hasSpan": true}, {"hasID": false, "type": "SEGMENT", "attrs": [{"type": "string", "name": "annotator", "aggregation": null}, {"type": "string", "name": "status", "aggregation": null}, {"type": "string", "name": "to_review", "aggregation": null}, {"type": "string", "name": "reviewed_by", "aggregation": null}], "annots": [[0, 5402, "GOLD_STANDARD", "reconciled"]], "hasSpan": true}], "version": 2, "metadata": {"phasesDone": ["tag", "truezone", "tokenize", "align", "zone and align"]}}