<RECORD ID="192">
<TEXT>
<ID>491550031</ID> <HOSPITAL>PUMC</HOSPITAL>
<ID>7258999</ID>
<ID>122832</ID>
<ID>328042</ID>
<DATE>1/19/2001</DATE> 12:00:00 AM
ED Discharge Summary
Unsigned
DIS
Report Status :
Unsigned
ED DISCHARGE NOTIFICATION / SUMMARY
<PATIENT>RHALTSAP , KANDDESS</PATIENT>
MRN :
<ID>7258999</ID>
Age :
43y
REGISTRATION DATE :
<DATE>01/19/2001</DATE> 01:11 AM
Provider :
<DOCTOR>Left Sumchirdkaysmavveindreps</DOCTOR> PRELIMINARY REPORT
Benefits Assigned :
Y
Discharge Date / Time :
<DATE>01/19/2001</DATE> 02:59
Discharge Status :
Discharged
Condition on Discharge :
Stable
Patient States Complaint :
MVA
Diagnosis :
1.) Cervical spine whiplash
2.) Sacral contusion
3.) Left hand sprain
Treatment Rendered :
Head , C-spine , and Abd CT scans normal .
Trauma series unremarkable
Discharge Medications :
Motrin 400-600 mg po three times a day with meals
Follow up Service :
It is recommended that you receive follow-up care in the Surgical Clinic if you notice fever , chills , nausea , vomiting , dizziness , or intense headaches .
To schedule an appt. , please call <PHONE>( 085 ) 062-8570</PHONE> between 8a.m. and 4:30p.m. Monday-Friday .
If you have a managed care plan , check with your PCP before making this appt .
Disposition , Follow up and Instructions to Patient :
Stable
PCP Name :
NONE , PHYSICIAN
Provider Number :
<ID>44824</ID>
This report was created by <DOCTOR>Sumchirdkaysmavveindreps , Yertrey</DOCTOR> <DATE>01/19/2001</DATE> 03:17 AM
[ report_end ]
</TEXT>
</RECORD>