{"signal": "\n\n119093641\nDischarge Summary\nUnsigned\nDIS\nAdmission Date :\n10/29/1990\nReport Status :\nUnsigned\nDischarge Date :\n11/09/1990\nDISCHARGE DIAGNOSES :\n1) STATUS POST ANTERIOR MYOCARDIAL INFARCTION LEADING TO CARDIAC ARREST .\n2) BILATERAL LUNG CARCINOMA .\n3) CONGESTIVE HEART FAILURE .\nHISTORY OF PRESENT ILLNESS :\nMr. Noun was a 71-year-old white gentleman with non-small lung CA of both upper lobes .\nNo metastatic disease , status post one course of chemotherapy with MVP ( Mitomycin-C , Vinblastin , and Platinum ) at the Petersly Hospital And Medical Center .\nHe was admitted on 10-29-90 because of pulmonary edema and ST wave changes .\nIn 07-90 he was shown to have bilateral upper lobe mass .\nChemotherapy consisted of Mitomycin-C , Vinblastin , Platinum .\nDenies orthopnea , PND .\nHe was seen in Petersly Hospital And Medical Center on 10-29-90 and EKG changes with ST elevations in V2 through V4 and flipped T waves in leads 3 and aVF was noted .\nHis O2 saturation on admission showed 90% on 100% face mask .\nThe patient was electively intubated and treated with morphine , Lasix , nitroglycerin , Nitro Paste , and sublingual Nifedipine .\nPAST MEDICAL HISTORY :\nNotable for bilateral apical lung cancer , history of urinary retention with a prostate specific antigen of 21.7 and a right prostate nodule .\nMEDICATIONS :\nMS Contin 60 mg po bid and Senekot .\nALLERGIES :\nNone .\nNicotine abuse , quit in the 80s , and rare alcohol .\nPHYSICAL EXAMINATION :\nIn general the patient was intubated , elderly gentleman on respirator .\nChest with bibasilar crackles , otherwise clear to auscultation .\nCarotids 2+ without bruits .\nAbdominal exam decreased bowel sounds , otherwise normal .\nThe rest of the physical exam was unremarkable .\nLABORATORY DATA :\nNotable for CK 111 with MB 0 .\nThe rest of the laboratory data wwas unremarkable .\nHis CK increased up to 1080 with an MB 63 .\nEKG showed ST elevations in leads V3 through V4 with flipped T waves in V2 through V4 .\nChest x-ray showed diffuse interstitial and alveolar abnormalities predominantly in the perihilar and basilar regions most consistent with CHF and large left perihilar mass and no pneumothorax .\nHOSPITAL COURSE :\n1) CHF and myocardial infarction - An IJ line was placed without complications on 10-30-90 .\nThe pressures were consistent with right heart and left heart failure .\nHe was treated with IV Lasix and IV Dopamine , nitroglycerin with good improvement .\nHis CK peaked at 1080 .\nThe patient was put on Captopril 12.5 mg po tid .\nNo aneurysm , no clot .\nETT performed on 11-6-90 showed 4 minutes 39 seconds on modified Bruce , stopped because of fatigue , no chest pain .\nImpression was non-diagnostic for ischemia in predischarge protocol .\nThe patient was ready for discharge , however , on 11-7-90 he was found to be in ventricular tachycardia , pulseless , unresponsive .\nCardiopulmonary resuscitation was initiated .\nThe patient had a CK leak up to 870 with an MB of 13 .\nThe patient electively decided not to be intubated nor resuscitated in case of another cardiac or respiratory arrest .\nOn 11-9-90 the patient again had ventricular tachycardia / ventricular fibrillation arrest .\nSince the patient had decided to be do not resuscitate no resuscitation efforts were undertaken and patient was pronounced dead on 11-9-90 at 5:10 a.m.\nAutopsy was performed .\nD :\n05/15/91\nBatch :\nReport :\nQ5498T3\nT :\nDicatated By :\nLEENROMO PRYDETITCHE , M.D.\n\n\n", "asets": [{"hasID": false, "type": "lex", "attrs": [], "annots": [[2, 11], [12, 21], [22, 29], [30, 38], [39, 42], [43, 52], [53, 57], [58, 59], [60, 62], [62, 63], [63, 65], [65, 66], [66, 70], [71, 77], [78, 84], [85, 86], [87, 95], [96, 105], [106, 110], [111, 112], [113, 115], [115, 116], [116, 118], [118, 119], [119, 123], [124, 133], [134, 143], [144, 145], [146, 147], [147, 148], [149, 155], [156, 160], [161, 169], [170, 180], [181, 191], [192, 199], [200, 202], [203, 210], [211, 217], [218, 219], [220, 221], [221, 222], [223, 232], [233, 237], [238, 247], [248, 249], [250, 251], [251, 252], [253, 263], [264, 269], [270, 277], [278, 279], [280, 287], [288, 290], [291, 298], [299, 306], [307, 308], [309, 312], [313, 317], [318, 321], [322, 323], [324, 326], [326, 335], [336, 341], [342, 351], [352, 356], [357, 366], [367, 371], [372, 374], [375, 377], [378, 382], [383, 388], [389, 394], [395, 396], [397, 399], [400, 410], [411, 418], [419, 420], [421, 427], [428, 432], [433, 436], [437, 443], [444, 446], [447, 459], [460, 464], [465, 468], [469, 470], [471, 482], [483, 484], [485, 495], [496, 497], [498, 501], [502, 510], [511, 512], [513, 515], [516, 519], [520, 528], [529, 537], [538, 541], [542, 549], [550, 556], [557, 558], [559, 561], [562, 565], [566, 574], [575, 577], [578, 586], [587, 594], [595, 597], [598, 607], [608, 613], [614, 617], [618, 620], [621, 625], [626, 633], [634, 635], [636, 638], [639, 644], [645, 647], [648, 651], [652, 657], [658, 660], [661, 665], [666, 675], [676, 681], [682, 686], [687, 691], [692, 693], [694, 706], [707, 716], [717, 719], [720, 731], [732, 733], [734, 744], [745, 746], [747, 755], [756, 757], [758, 764], [765, 774], [775, 776], [777, 780], [781, 782], [783, 785], [786, 789], [790, 794], [795, 797], [798, 806], [807, 815], [816, 819], [820, 827], [828, 834], [835, 837], [838, 846], [847, 850], [851, 854], [855, 862], [863, 867], [868, 870], [871, 881], [882, 884], [885, 887], [888, 895], [896, 898], [899, 902], [903, 910], [911, 912], [913, 918], [919, 921], [922, 927], [928, 929], [930, 933], [934, 937], [938, 941], [942, 947], [948, 949], [950, 953], [954, 956], [957, 967], [968, 970], [971, 980], [981, 987], [988, 991], [992, 994], [995, 999], [1000, 1004], [1005, 1009], [1010, 1011], [1012, 1015], [1016, 1023], [1024, 1027], [1028, 1038], [1039, 1048], [1049, 1052], [1053, 1060], [1061, 1065], [1066, 1074], [1075, 1076], [1077, 1082], [1083, 1084], [1085, 1098], [1099, 1100], [1101, 1106], [1107, 1112], [1113, 1114], [1115, 1118], [1119, 1129], [1130, 1140], [1141, 1142], [1143, 1147], [1148, 1155], [1156, 1163], [1164, 1165], [1166, 1173], [1174, 1177], [1178, 1187], [1188, 1194], [1195, 1199], [1200, 1206], [1207, 1208], [1209, 1216], [1217, 1219], [1220, 1227], [1228, 1237], [1238, 1242], [1243, 1244], [1245, 1253], [1254, 1262], [1263, 1270], [1271, 1273], [1274, 1278], [1279, 1282], [1283, 1284], [1285, 1290], [1291, 1299], [1300, 1306], [1307, 1308], [1309, 1320], [1321, 1322], [1323, 1325], [1326, 1332], [1333, 1335], [1336, 1338], [1339, 1341], [1342, 1345], [1346, 1349], [1350, 1357], [1358, 1359], [1360, 1369], [1370, 1371], [1372, 1376], [1377, 1378], [1379, 1387], [1388, 1393], [1394, 1395], [1396, 1400], [1401, 1403], [1404, 1407], [1408, 1411], [1412, 1413], [1414, 1417], [1418, 1422], [1423, 1430], [1431, 1432], [1433, 1441], [1442, 1453], [1454, 1455], [1456, 1458], [1459, 1466], [1467, 1470], [1471, 1478], [1479, 1482], [1483, 1492], [1493, 1494], [1495, 1502], [1503, 1512], [1513, 1515], [1516, 1526], [1527, 1528], [1529, 1534], [1535, 1539], [1540, 1549], [1550, 1558], [1559, 1560], [1561, 1570], [1571, 1576], [1577, 1579], [1580, 1592], [1593, 1594], [1595, 1603], [1604, 1605], [1605, 1606], [1607, 1614], [1615, 1621], [1622, 1623], [1624, 1633], [1634, 1638], [1639, 1648], [1649, 1654], [1655, 1661], [1662, 1663], [1664, 1673], [1674, 1680], [1681, 1682], [1683, 1686], [1687, 1691], [1692, 1694], [1695, 1698], [1699, 1707], [1708, 1712], [1713, 1716], [1717, 1729], [1730, 1731], [1732, 1742], [1743, 1747], [1748, 1749], [1750, 1757], [1758, 1761], [1762, 1764], [1765, 1768], [1769, 1773], [1774, 1776], [1777, 1778], [1779, 1780], [1781, 1784], [1785, 1789], [1790, 1792], [1793, 1796], [1797, 1807], [1808, 1812], [1813, 1817], [1818, 1830], [1831, 1832], [1833, 1836], [1837, 1839], [1840, 1849], [1850, 1852], [1853, 1855], [1856, 1860], [1861, 1865], [1866, 1868], [1869, 1871], [1872, 1874], [1875, 1876], [1877, 1880], [1881, 1887], [1888, 1890], [1891, 1901], [1902, 1904], [1905, 1910], [1911, 1913], [1914, 1921], [1922, 1924], [1925, 1929], [1930, 1937], [1938, 1939], [1940, 1945], [1946, 1948], [1949, 1951], [1952, 1959], [1960, 1962], [1963, 1964], [1965, 1970], [1971, 1976], [1977, 1983], [1984, 1991], [1992, 2004], [2005, 2008], [2009, 2017], [2018, 2031], [2032, 2045], [2046, 2048], [2049, 2052], [2053, 2062], [2063, 2066], [2067, 2074], [2075, 2082], [2083, 2087], [2088, 2098], [2099, 2103], [2104, 2107], [2108, 2111], [2112, 2117], [2118, 2122], [2123, 2132], [2133, 2137], [2138, 2141], [2142, 2144], [2145, 2157], [2158, 2159], [2160, 2168], [2169, 2175], [2176, 2177], [2178, 2179], [2179, 2180], [2181, 2184], [2185, 2188], [2189, 2199], [2200, 2210], [2211, 2212], [2213, 2215], [2216, 2218], [2219, 2223], [2224, 2227], [2228, 2234], [2235, 2242], [2243, 2256], [2257, 2259], [2260, 2268], [2269, 2270], [2271, 2274], [2275, 2284], [2285, 2289], [2290, 2300], [2301, 2305], [2306, 2311], [2312, 2317], [2318, 2321], [2322, 2326], [2327, 2332], [2333, 2340], [2341, 2342], [2343, 2345], [2346, 2349], [2350, 2357], [2358, 2362], [2363, 2365], [2366, 2371], [2372, 2375], [2376, 2378], [2379, 2387], [2388, 2389], [2390, 2403], [2404, 2408], [2409, 2413], [2414, 2425], [2426, 2427], [2428, 2431], [2432, 2434], [2435, 2441], [2442, 2444], [2445, 2449], [2450, 2451], [2452, 2455], [2456, 2463], [2464, 2467], [2468, 2471], [2472, 2474], [2475, 2484], [2485, 2489], [2490, 2492], [2493, 2495], [2496, 2499], [2500, 2501], [2502, 2504], [2505, 2513], [2514, 2515], [2516, 2518], [2519, 2523], [2524, 2525], [2526, 2529], [2530, 2539], [2540, 2542], [2543, 2550], [2551, 2557], [2558, 2559], [2560, 2567], [2568, 2570], [2571, 2578], [2579, 2581], [2582, 2590], [2591, 2596], [2597, 2598], [2599, 2606], [2607, 2614], [2615, 2617], [2618, 2625], [2626, 2627], [2628, 2630], [2631, 2636], [2637, 2641], [2642, 2643], [2644, 2654], [2655, 2658], [2659, 2673], [2674, 2677], [2678, 2686], [2687, 2689], [2690, 2702], [2703, 2711], [2712, 2713], [2714, 2717], [2718, 2725], [2726, 2729], [2730, 2735], [2736, 2739], [2740, 2749], [2750, 2751], [2752, 2759], [2760, 2761], [2762, 2764], [2765, 2772], [2773, 2775], [2776, 2779], [2780, 2785], [2786, 2788], [2789, 2791], [2792, 2794], [2795, 2806], [2807, 2818], [2819, 2820], [2821, 2830], [2831, 2832], [2833, 2845], [2846, 2847], [2848, 2863], [2864, 2877], [2878, 2881], [2882, 2891], [2892, 2893], [2894, 2897], [2898, 2905], [2906, 2909], [2910, 2911], [2912, 2914], [2915, 2919], [2920, 2922], [2923, 2925], [2926, 2929], [2930, 2934], [2935, 2937], [2938, 2940], [2941, 2943], [2944, 2946], [2947, 2948], [2949, 2952], [2953, 2960], [2961, 2971], [2972, 2979], [2980, 2983], [2984, 2986], [2987, 2989], [2990, 2999], [3000, 3003], [3004, 3016], [3017, 3019], [3020, 3024], [3025, 3027], [3028, 3035], [3036, 3043], [3044, 3046], [3047, 3058], [3059, 3065], [3066, 3067], [3068, 3070], [3071, 3078], [3079, 3082], [3083, 3090], [3091, 3096], [3097, 3100], [3101, 3112], [3113, 3124], [3125, 3126], [3127, 3138], [3139, 3151], [3152, 3158], [3159, 3160], [3161, 3166], [3167, 3170], [3171, 3178], [3179, 3182], [3183, 3190], [3191, 3193], [3194, 3196], [3197, 3199], [3200, 3203], [3204, 3215], [3216, 3218], [3219, 3232], [3233, 3240], [3241, 3245], [3246, 3256], [3257, 3260], [3261, 3268], [3269, 3272], [3273, 3283], [3284, 3288], [3289, 3291], [3292, 3299], [3300, 3302], [3303, 3304], [3304, 3305], [3305, 3307], [3308, 3310], [3310, 3312], [3313, 3320], [3321, 3324], [3325, 3334], [3335, 3336], [3337, 3338], [3339, 3340], [3341, 3343], [3343, 3344], [3344, 3346], [3346, 3347], [3347, 3349], [3350, 3355], [3356, 3357], [3358, 3364], [3365, 3366], [3367, 3374], [3375, 3376], [3377, 3378], [3379, 3388], [3389, 3391], [3392, 3393], [3394, 3402], [3403, 3414], [3415, 3416], [3417, 3419], [3419, 3421]], "hasSpan": true}, {"hasID": false, "type": "zone", "attrs": [{"type": "string", "name": "region_type", "aggregation": null}], "annots": [[0, 3424, "body"]], "hasSpan": true}, {"hasID": false, "type": "HOSPITAL", "attrs": [], "annots": [[520, 556], [798, 834]], "hasSpan": true}, {"hasID": false, "type": "ID", "attrs": [], "annots": [[2, 11], [3367, 3374]], "hasSpan": true}, {"hasID": false, "type": "DOCTOR", "attrs": [], "annots": [[3394, 3414]], "hasSpan": true}, {"hasID": false, "type": "PATIENT", "attrs": [], "annots": [[313, 317]], "hasSpan": true}, {"hasID": false, "type": "SEGMENT", "attrs": [{"type": "string", "name": "annotator", "aggregation": null}, {"type": "string", "name": "status", "aggregation": null}, {"type": "string", "name": "to_review", "aggregation": null}, {"type": "string", "name": "reviewed_by", "aggregation": null}], "annots": [[0, 3424, "GOLD_STANDARD", "reconciled"]], "hasSpan": true}, {"hasID": false, "type": "DATE", "attrs": [], "annots": [[60, 70], [113, 123], [578, 586], [639, 644], [838, 846], [2260, 2268], [2543, 2550], [2765, 2772], [3071, 3078], [3292, 3299], [3341, 3349]], "hasSpan": true}], "version": 2, "metadata": {"phasesDone": ["tag", "truezone", "tokenize", "align", "zone and align"]}}