<RECORD ID="360">
<TEXT>
<ID>985213692</ID> <HOSPITAL>WGH</HOSPITAL>
<ID>8894679</ID>
<ID>77279</ID>
<ID>1063544</ID>
<DATE>8/14/2003</DATE> 12:00:00 AM
OB Discharge Summary
Signed
DIS
Report Status :
Signed OB EMR L and D
DISCHARGE SUMMARY
NAME :
<PATIENT>BETLA CHECK</PATIENT>
UNIT NUMBER :
<ID>393-00-85</ID>
ADMISSION DATE :
<DATE>20030814</DATE>
DISCHARGE DATE :
<DATE>20030816</DATE>
PRINCIPAL DISCHARGE DIAGNOSIS :
Normal Vaginal Delivery
ASSOCIATED DIAGNOSES :
Acute Urinary Tract Infection ; Heart Murmur , history of
PRINCIPAL PROCEDURE OR OPERATION :
Spontaneous Vertex Vaginal Delivery
ASSOCIATED PROCEDURES OR OPERATIONS :
POSTPARTUM DIAGNOSTIC PROCEDURES :
None
POSTPARTUM THERAPEUTIC PROCEDURES :
None
OTHER POSTPARTUM THERAPIES :
Routine Post Partum Care
HISTORY AND REASON FOR HOSPITALIZATION :
Active Labor
PHYSICAL EXAMINATION :
HEIGHT 61 HEENT NORMAL MOUTH NORMAL NECK NORMAL BREASTS right breast 11 oclock , left breast , 11o clock NIPPLES NORMAL CHEST NORMAL COR ( + ) diastolic murmur ABDOMEN NORMAL Gravid , FHR 130-140s good variability without decels , neg .
CST EXTREM NORMAL SKIN NORMAL NODES NORMAL VULVA NORMAL VAGINA NORMAL CERVIX NORMAL 3/80/-1 vtx .
BOWI OS NORMAL ADNEXAE NORMAL UTERUS NORMAL UTERINE SIZE IN WEEKS NORMAL 40
HOSPITAL COURSE ( include complications if any ) :
This 24 year old Gravida 1 Para 0000 was admitted to the <HOSPITAL>Life Valley Medical Center</HOSPITAL> Obstetrical service on <DATE>08/14/2003</DATE> at 01:01 pm for the indication ( s ) :
active labor .
She delivered a 3292 gram female infant on <DATE>08/14/2003</DATE> at 06:46 pm with apgar scores of 8 and 9 at one and five minutes respectively at 39.3 weeks gestation via spontaneous vertex vaginal delivery .
During her labor she encountered the following complication ( s ) :
none .
During her delivery she encountered the following complication ( s ) :
nuchal cord , x1 - easily reduced .
Postpartum she encountered the following complication ( s ) :
none .
She was discharged on <DATE>08/16/2003</DATE> at 12:00 pm in good condition .
DISCHARGE ORDERS ( medications instructions to patient , follow-up care ) :
DISCHARGE ACTIVITY :
No Restrictions
DISCHARGE DIET :
No Restrictions
POSTPARTUM DISPOSITION :
Home With Self-Care ( Routine Discharge )
POSTPARTUM CARE SITE :
<HOSPITAL>Erloff Hospital</HOSPITAL>
POSTPARTUM RETURN APPOINTMENT ( DAYS ) :
42
BREAST FEEDING AT DISCHARGE :
Yes
POSTPARTUM RH IMMUNE GLOBULIN :
Not Indicated
POSTPARTUM MEASLES / MUMPS / RUBELLA VACCINE :
Not Indicated
MEDICATION ( S ) ON DISCHARGE :
Gentamicin Injection ; Multivitamins And Iron
Electronically Signed :
<DOCTOR>Ockgiernruss , Riret R</DOCTOR> <DATE>12/09/2003</DATE> 8:48:51 PM
[ report_end ]
</TEXT>
</RECORD>