<RECORD ID="791">
<TEXT>
<ID>478865872</ID>
<HOSPITAL>PUOMC</HOSPITAL>
<ID>82331</ID>
<ID>408058</ID>
<DATE>2/6/1997</DATE> 12:00:00 AM
Discharge Summary
DIS
Report Status :
NAME :
<PATIENT>SHUFF , RONHUM</PATIENT>
<DATE>02/06/97</DATE>
Lump in anterior abdominal / groin area .
HISTORY OF PRESENT ILLNESS :
This was initially in 1993 , followed shortly thereafter by repair of a thoracoabdominal aneurysm with an aortobifemoral bypass graft .
She reports approximately 48 hours prior to this developing pain in the right lower abdomen and groin and noticed a new onset of a lump .
The past medical history and past surgical history is significant for upper gastrointestinal bleed , chronic obstructive pulmonary disease , history of hypertension , atrial fibrillation .
MEDICATIONS ON ADMISSION :
Prilosec , Lanoxin , Lescol .
The physical examination reveals a thin woman in no acute distress .
Abdomen :
soft with a palpable , nonpulsatile mass in the right lower abdomen which measures approximately 3 centimeters x 3 centimeters .
HOSPITAL COURSE AND TREATMENT :
The patient does have a known large ascending aortic aneurysm and while she was admitted , this was studied with a chest computerized tomography scan .
The wounds were closed primarily .
The patient tolerated the procedure well .
MEDICATIONS ON DISCHARGE :
Include the addition of Bactrim DS one tablet PO b.i.d. x five days , Percocet 1-2 PO q4h prn .
<DOCTOR>TA JESC</DOCTOR> , M.D.
DICTATING FOR :
___________________________ <DOCTOR>RIODE R. RAY</DOCTOR> , M.D.
<DOCTOR>zbb</DOCTOR>
DD :
<DATE>02/11/97</DATE>
TD :
<DATE>02/15/97</DATE> 11:04 A
<DOCTOR>RIODE REYAZA RAY</DOCTOR> , M.D.
</TEXT>
</RECORD>