<RECORD ID="807">
<TEXT>
<ID>710832021</ID>
<ID>9066323</ID>
<DATE>8/29/1997</DATE> 12:00:00 AM
HEART FAILURE .
PULMONARY HYPERTENSION .
MITRAL
Unsigned
Report Status :
<PATIENT>ZISK , MAPI T</PATIENT>
UNIT NUMBER :
<ID>093-80-10</ID>
Mitral stenosis .
Bacteremia .
Heparin induced thrombocytopenia .
Echocardiogram which showed a mitral valve area 1.1cm2 , a mean gradient of 6 , mild mitral regurgitation , normal left ventricular function , moderate to severe tricuspid regurgitation , pulmonary hypertension , right ventricular systolic pressure of 60 , and right ventricular diffusely hypokinetic .
HISTORY OF PRESENT ILLNESS :
The patient is 57 years old with a history of a rheumatic heart , mitral stenosis , pulmonary hypertension who was transferred to <HOSPITAL>Ph University Of Medical Center</HOSPITAL> from <HOSPITAL>E Health</HOSPITAL> for evaluation of possible mitral valve prolapseplasty .
Issues on admission :
The patient was also on Flolan .
2. The patient had atrial fibrillation on admission which improved with Verapamil .
Hematology was consult and the thrombocytopenia was likely due to Heparin .
The Heparin was stopped and Coumadin was started .
The patient was treated with Vancomycin for 5-6 weeks until <DATE>9/29/97</DATE> before an valvuloplasty can be done .
The patient also had right upper quadrant pain during hospitalization at <HOSPITAL>Ph University Of Medical Center</HOSPITAL> .
The patient had a Hiter scan which was negative and it was thought that the right upper quadrant pain was due to liver congestion .
PHYSICAL EXAMINATION :
JVD elevated 72mm of H20 .
Her heart exam revealed an irregular rhythm with a II over VI diastolic murmur at the apex .
Her abdomen was positive for an ascitic wave and her extremities showed 2+ edema .
The patient had dysorthopnia .
LABORATORY DATA :
Right ventricular hypertrophy and right axis deviation .
Continue with Vancomycin until <DATE>9/29/97</DATE> , presently on hold until the level are rechecked .
Continue with Coumadin , presently on hold because her INR is 5.6 .
Continue with Flolan .
Continue with Lasix 100mg. Continue with Dyuril .
Continue with inhalers , Albuterol .
Synthroid .
TR :
<DOCTOR>ng</DOCTOR>
TD :
cc :
</TEXT>
</RECORD>