<RECORD ID="746">
<TEXT>
<ID>688439328</ID>
<HOSPITAL>CTMC</HOSPITAL>
<ID>164980</ID>
<DATE>11/2/1990</DATE> 12:00:00 AM
Discharge Summary
Unsigned
DIS
Admission Date :
<DATE>11/02/1990</DATE>
Report Status :
Unsigned
1) MITRAL STENOSIS .
2) HYPERTENSION .
3) ATRIAL FIBRILLATION .
4) HYPERCHOLESTEROLEMIA .
HISTORY OF PRESENT ILLNESS :
The patient was told that she had a heart murmur approximately twenty years ago .
However , she had been asymptomatic at that time .
She now gives a history of progressively worsening dyspnea on exertion and fatigue which has become more incapacitating over the past several months .
She states that previously , she had been fairly active but now does not feel that she can do much of anything .
She also complains of a tight feeling in her abdomen .
She also has had a cough for the past several years which is worse in the wintertime and is non-productive .
The patient &apos;s cardiac risk factors include a positive family history in that both parents died in their fifties of heart disease and two brothers had coronary artery bypass graft procedures in their thirties , hypercholesterolemia for several years , and hypertension .
There is no history of rheumatic heart disease recalled by the patient , removal of benign lump in the left breast .
ALLERGIES :
SOCIAL HISTORY :
The patient lives with her husband in <LOCATION>Glendmin</LOCATION> .
She has four children , ages 22 through 27 , and works as a cook at a grammer school .
HEENT :
Unremarkable .
Clear to auscultation and percussion .
Carotid arteries showed normal upstroke and volume without bruits bilaterally .
There was jugular venous distention to l7 cm at 45 degrees .
The point of maximal impulse was at the fifth intercostal space in the mid clavicular line .
There was a left parasternal lift .
NEUROLOGICAL :
However , there was evidence of subtle mental status change on the evening after the patient &apos;s valvuloplasty .
She was having difficulty remembering certain events which had occurred that day .
It was felt that because her neurological examination was non-focal at this time and that these changes represented no real change in her mental status from the time of admission , that no further work-up was required .
DISCHARGE MEDICATIONS :
Nadalol 20 mg p.o. q.d. , Coumadin 5 mg p.o. q.h.s. , Mevacor 20 mg q.d. , and Digoxin 0.25 mg q.d.
________________________________ <ID>SQ869/0059</ID> <DOCTOR>CA G. NERMOONE</DOCTOR> , M.D. <ID>XO4</ID>
<DATE>11/06/90</DATE>
<ID>2762</ID>
<ID>Z3569C89</ID>
T :
<DOCTOR>RA LERKNEIGHKIH</DOCTOR> , <ID>ZBE5</ID>
</TEXT>
</RECORD>